codemcp/__init__.py
codemcp/__main__.py
codemcp/access.py
codemcp/agno.py
codemcp/async_file_utils.py
codemcp/code_command.py
codemcp/common.py
codemcp/config.py
codemcp/file_utils.py
codemcp/git.py
codemcp/git_commit.py
codemcp/git_message.py
codemcp/git_parse_message.py
codemcp/git_query.py
codemcp/glob_pattern.py
codemcp/hot_reload_entry.py
codemcp/line_endings.py
codemcp/main.py
codemcp/multi_entry.py
codemcp/rules.py
codemcp/shell.py
codemcp/testing.py
codemcp/templates/README.md
codemcp/templates/blank/codemcp.toml
codemcp/templates/python/README.md
codemcp/templates/python/codemcp.toml
codemcp/templates/python/pyproject.toml
codemcp/templates/python/__PACKAGE_NAME__/__init__.py
codemcp/templates/python/__PACKAGE_NAME__/py.typed
codemcp/templates/python/__PACKAGE_NAME__/_internal/__init__.py
codemcp/tools/__init__.py
codemcp/tools/chmod.py
codemcp/tools/edit_file.py
codemcp/tools/git_blame.py
codemcp/tools/git_diff.py
codemcp/tools/git_log.py
codemcp/tools/git_show.py
codemcp/tools/glob.py
codemcp/tools/grep.py
codemcp/tools/init_project.py
codemcp/tools/ls.py
codemcp/tools/read_file.py
codemcp/tools/rm.py
codemcp/tools/run_command.py
codemcp/tools/think.py
codemcp/tools/user_prompt.py
codemcp/tools/write_file.py
codemcp-0.6.0.dist-info/METADATA
codemcp-0.6.0.dist-info/WHEEL
codemcp-0.6.0.dist-info/entry_points.txt
codemcp-0.6.0.dist-info/licenses/LICENSE.txt
codemcp-0.6.0.dist-info/RECORD
