Metadata-Version: 2.4
Name: codemcp
Version: 0.6.0
Summary: MCP server for file operations
License: MIT
License-File: LICENSE.txt
Requires-Python: >=3.12
Requires-Dist: agno>=1.2.16
Requires-Dist: anthropic>=0.49.0
Requires-Dist: anyio>=3.7.0
Requires-Dist: click>=8.1.8
Requires-Dist: editorconfig>=0.17.0
Requires-Dist: fastapi>=0.115.12
Requires-Dist: google-genai>=1.10.0
Requires-Dist: mcp[cli]>=1.2.0
Requires-Dist: pathspec>=0.12.1
Requires-Dist: pyyaml>=6.0.0
Requires-Dist: ruff>=0.9.10
Requires-Dist: starlette>=0.35.1
Requires-Dist: toml>=0.10.2
Requires-Dist: tomli>=2.1.1
Requires-Dist: uvicorn>=0.28.0
